[{"id":"monster-aPDefXYJ","date":"2018-06-25T06:52:02.832Z","caption":"Pacific Dire Weasel","postedToGit":true,"htmlFragment":"<li class=\"pane\">\n  <div class=\"time-stamp entry-meta\">\n    <a href=\"monster-aPDefXYJ.html\">\n      <time datetime=\"2018-06-25T06:52:02.832Z\">2018-6-25 02:52:02</time>\n    </a>\n  </div><div class=\"text-caption\">Pacific Dire Weasel</div>\n</li>","postedSingleVideoPage":true},{"id":"monster-xkEFZzLY","date":"2018-06-25T15:52:02.637Z","caption":"Titanium Penguin","postedToGit":true,"htmlFragment":"<li class=\"pane\">\n  <div class=\"time-stamp entry-meta\">\n    <a href=\"monster-xkEFZzLY.html\">\n      <time datetime=\"2018-06-25T15:52:02.637Z\">2018-6-25 11:52:02</time>\n    </a>\n  </div><div class=\"text-caption\">Titanium Penguin</div>\n</li>","postedSingleVideoPage":true},{"id":"monster-NeHtXjtF","date":"2018-06-26T00:52:03.333Z","caption":"Gmail Dire Bear","postedToGit":true,"htmlFragment":"<li class=\"pane\">\n  <div class=\"time-stamp entry-meta\">\n    <a href=\"monster-NeHtXjtF.html\">\n      <time datetime=\"2018-06-26T00:52:03.333Z\">2018-6-25 20:52:03</time>\n    </a>\n  </div><div class=\"text-caption\">Gmail Dire Bear</div>\n</li>","postedSingleVideoPage":true},{"id":"monster-UYXBvvBv","date":"2018-06-26T06:52:01.998Z","caption":"Visayan Sea Shrew","postedToGit":true,"htmlFragment":"<li class=\"pane\">\n  <div class=\"time-stamp entry-meta\">\n    <a href=\"monster-UYXBvvBv.html\">\n      <time datetime=\"2018-06-26T06:52:01.998Z\">2018-6-26 02:52:01</time>\n    </a>\n  </div><div class=\"text-caption\">Visayan Sea Shrew</div>\n</li>","postedSingleVideoPage":true},{"id":"monster-JMuoWNOv","date":"2018-06-26T15:52:02.110Z","caption":"Victim Kingfisher","postedToGit":true,"htmlFragment":"<li class=\"pane\">\n  <div class=\"time-stamp entry-meta\">\n    <a href=\"monster-JMuoWNOv.html\">\n      <time datetime=\"2018-06-26T15:52:02.110Z\">2018-6-26 11:52:02</time>\n    </a>\n  </div><div class=\"text-caption\">Victim Kingfisher</div>\n</li>","postedSingleVideoPage":true},{"id":"monster-vTeMLeYz","date":"2018-06-27T06:52:02.793Z","caption":"Chenille Shark","postedToGit":true,"htmlFragment":"<li class=\"pane\">\n  <div class=\"time-stamp entry-meta\">\n    <a href=\"monster-vTeMLeYz.html\">\n      <time datetime=\"2018-06-27T06:52:02.793Z\">2018-6-27 02:52:02</time>\n    </a>\n  </div><div class=\"text-caption\">Chenille Shark</div>\n</li>","postedSingleVideoPage":true},{"id":"monster-fdvnkHIw","date":"2018-06-27T15:52:01.961Z","caption":"Radków Grig","postedToGit":true,"htmlFragment":"<li class=\"pane\">\n  <div class=\"time-stamp entry-meta\">\n    <a href=\"monster-fdvnkHIw.html\">\n      <time datetime=\"2018-06-27T15:52:01.961Z\">2018-6-27 11:52:01</time>\n    </a>\n  </div><div class=\"text-caption\">Radków Grig</div>\n</li>","postedSingleVideoPage":true},{"id":"monster-oqQitkoZ","date":"2018-06-28T00:52:03.338Z","caption":"Snake Natu","postedToGit":true,"htmlFragment":"<li class=\"pane\">\n  <div class=\"time-stamp entry-meta\">\n    <a href=\"monster-oqQitkoZ.html\">\n      <time datetime=\"2018-06-28T00:52:03.338Z\">2018-6-27 20:52:03</time>\n    </a>\n  </div><div class=\"text-caption\">Snake Natu</div>\n</li>","postedSingleVideoPage":true},{"id":"monster-vSxhrpVP","date":"2018-06-28T06:52:02.622Z","caption":"Timber Gorebyss","postedToGit":true,"htmlFragment":"<li class=\"pane\">\n  <div class=\"time-stamp entry-meta\">\n    <a href=\"monster-vSxhrpVP.html\">\n      <time datetime=\"2018-06-28T06:52:02.622Z\">2018-6-28 02:52:02</time>\n    </a>\n  </div><div class=\"text-caption\">Timber Gorebyss</div>\n</li>","postedSingleVideoPage":true},{"id":"monster-iNtKXjJs","date":"2018-06-28T15:52:02.158Z","caption":"Zhu Jiang Ledian","postedToGit":true,"htmlFragment":"<li class=\"pane\">\n  <div class=\"time-stamp entry-meta\">\n    <a href=\"monster-iNtKXjJs.html\">\n      <time datetime=\"2018-06-28T15:52:02.158Z\">2018-6-28 11:52:02</time>\n    </a>\n  </div><div class=\"text-caption\">Zhu Jiang Ledian</div>\n</li>","postedSingleVideoPage":true},{"id":"monster-FmMybOSP","date":"2018-06-29T00:52:02.860Z","caption":"Polypropylene Devourer","postedToGit":true,"htmlFragment":"<li class=\"pane\">\n  <div class=\"time-stamp entry-meta\">\n    <a href=\"monster-FmMybOSP.html\">\n      <time datetime=\"2018-06-29T00:52:02.860Z\">2018-6-28 20:52:02</time>\n    </a>\n  </div><div class=\"text-caption\">Polypropylene Devourer</div>\n</li>","postedSingleVideoPage":true},{"id":"monster-GotieSZm","date":"2018-06-29T06:52:02.663Z","caption":"Apparel Worker Coyote","postedToGit":true,"htmlFragment":"<li class=\"pane\">\n  <div class=\"time-stamp entry-meta\">\n    <a href=\"monster-GotieSZm.html\">\n      <time datetime=\"2018-06-29T06:52:02.663Z\">2018-6-29 02:52:02</time>\n    </a>\n  </div><div class=\"text-caption\">Apparel Worker Coyote</div>\n</li>","postedSingleVideoPage":true},{"id":"monster-ncEKRuZY","date":"2018-06-29T15:52:02.628Z","caption":"Rock Bearded Devil","postedToGit":true,"htmlFragment":"<li class=\"pane\">\n  <div class=\"time-stamp entry-meta\">\n    <a href=\"monster-ncEKRuZY.html\">\n      <time datetime=\"2018-06-29T15:52:02.628Z\">2018-6-29 11:52:02</time>\n    </a>\n  </div><div class=\"text-caption\">Rock Bearded Devil</div>\n</li>","postedSingleVideoPage":true},{"id":"monster-pREQYVgn","date":"2018-06-30T00:52:03.246Z","caption":"Bureaucrat Porpoise","postedToGit":true,"htmlFragment":"<li class=\"pane\">\n  <div class=\"time-stamp entry-meta\">\n    <a href=\"monster-pREQYVgn.html\">\n      <time datetime=\"2018-06-30T00:52:03.246Z\">2018-6-29 20:52:03</time>\n    </a>\n  </div><div class=\"text-caption\">Bureaucrat Porpoise</div>\n</li>","postedSingleVideoPage":true},{"id":"monster-ZrWkDSwn","date":"2018-06-30T06:52:02.348Z","caption":"Tears Couatl","postedToGit":true,"htmlFragment":"<li class=\"pane\">\n  <div class=\"time-stamp entry-meta\">\n    <a href=\"monster-ZrWkDSwn.html\">\n      <time datetime=\"2018-06-30T06:52:02.348Z\">2018-6-30 02:52:02</time>\n    </a>\n  </div><div class=\"text-caption\">Tears Couatl</div>\n</li>","postedSingleVideoPage":true},{"id":"monster-NMttTeAm","date":"2018-06-30T15:52:02.330Z","caption":"Northern Dvina Cormorant","postedToGit":true,"htmlFragment":"<li class=\"pane\">\n  <div class=\"time-stamp entry-meta\">\n    <a href=\"monster-NMttTeAm.html\">\n      <time datetime=\"2018-06-30T15:52:02.330Z\">2018-6-30 11:52:02</time>\n    </a>\n  </div><div class=\"text-caption\">Northern Dvina Cormorant</div>\n</li>","postedSingleVideoPage":true},{"id":"monster-PZfPUHTT","date":"2018-07-01T00:52:02.994Z","caption":"Shadow Nodens","postedToGit":true,"htmlFragment":"<li class=\"pane\">\n  <div class=\"time-stamp entry-meta\">\n    <a href=\"monster-PZfPUHTT.html\">\n      <time datetime=\"2018-07-01T00:52:02.994Z\">2018-6-30 20:52:02</time>\n    </a>\n  </div><div class=\"text-caption\">Shadow Nodens</div>\n</li>","postedSingleVideoPage":true},{"id":"monster-oTqkXhqm","date":"2018-07-01T06:52:02.383Z","caption":"Sycophant Archon","postedToGit":true,"htmlFragment":"<li class=\"pane\">\n  <div class=\"time-stamp entry-meta\">\n    <a href=\"monster-oTqkXhqm.html\">\n      <time datetime=\"2018-07-01T06:52:02.383Z\">2018-7-1 02:52:02</time>\n    </a>\n  </div><div class=\"text-caption\">Sycophant Archon</div>\n</li>","postedSingleVideoPage":true},{"id":"monster-NPZfeMZM","date":"2018-07-01T15:52:02.812Z","caption":"Screamin' Green Fire Beetle","postedToGit":true,"htmlFragment":"<li class=\"pane\">\n  <div class=\"time-stamp entry-meta\">\n    <a href=\"monster-NPZfeMZM.html\">\n      <time datetime=\"2018-07-01T15:52:02.812Z\">2018-7-1 11:52:02</time>\n    </a>\n  </div><div class=\"text-caption\">Screamin' Green Fire Beetle</div>\n</li>","postedSingleVideoPage":true},{"id":"monster-BLWaeOwA","date":"2018-07-02T00:52:03.549Z","caption":"Rock Dodongo","postedToGit":true,"htmlFragment":"<li class=\"pane\">\n  <div class=\"time-stamp entry-meta\">\n    <a href=\"monster-BLWaeOwA.html\">\n      <time datetime=\"2018-07-02T00:52:03.549Z\">2018-7-1 20:52:03</time>\n    </a>\n  </div><div class=\"text-caption\">Rock Dodongo</div>\n</li>","postedSingleVideoPage":true},{"id":"monster-RvbvaOys","date":"2018-07-02T06:52:02.151Z","caption":"Southern Dire Lion","postedToGit":true,"htmlFragment":"<li class=\"pane\">\n  <div class=\"time-stamp entry-meta\">\n    <a href=\"monster-RvbvaOys.html\">\n      <time datetime=\"2018-07-02T06:52:02.151Z\">2018-7-2 02:52:02</time>\n    </a>\n  </div><div class=\"text-caption\">Southern Dire Lion</div>\n</li>","postedSingleVideoPage":true},{"id":"monster-USIkvvcL","date":"2018-07-02T15:52:02.147Z","caption":"Haven Shub-Niggurath","postedToGit":true,"htmlFragment":"<li class=\"pane\">\n  <div class=\"time-stamp entry-meta\">\n    <a href=\"monster-USIkvvcL.html\">\n      <time datetime=\"2018-07-02T15:52:02.147Z\">2018-7-2 11:52:02</time>\n    </a>\n  </div><div class=\"text-caption\">Haven Shub-Niggurath</div>\n</li>","postedSingleVideoPage":true},{"id":"monster-ZFXzCEDc","date":"2018-07-03T00:52:02.762Z","caption":"Mercerised Cotton Wraith","postedToGit":true,"htmlFragment":"<li class=\"pane\">\n  <div class=\"time-stamp entry-meta\">\n    <a href=\"monster-ZFXzCEDc.html\">\n      <time datetime=\"2018-07-03T00:52:02.762Z\">2018-7-2 20:52:02</time>\n    </a>\n  </div><div class=\"text-caption\">Mercerised Cotton Wraith</div>\n</li>","postedSingleVideoPage":true},{"id":"monster-vFFIxJYp","date":"2018-07-03T06:52:02.132Z","caption":"Tickle Me Pink Chaos Beast","postedToGit":true,"htmlFragment":"<li class=\"pane\">\n  <div class=\"time-stamp entry-meta\">\n    <a href=\"monster-vFFIxJYp.html\">\n      <time datetime=\"2018-07-03T06:52:02.132Z\">2018-7-3 02:52:02</time>\n    </a>\n  </div><div class=\"text-caption\">Tickle Me Pink Chaos Beast</div>\n</li>","postedSingleVideoPage":true},{"id":"monster-XXatdKhH","date":"2018-07-03T15:52:02.477Z","caption":"Nasławice Ghoul","postedToGit":true,"htmlFragment":"<li class=\"pane\">\n  <div class=\"time-stamp entry-meta\">\n    <a href=\"monster-XXatdKhH.html\">\n      <time datetime=\"2018-07-03T15:52:02.477Z\">2018-7-3 11:52:02</time>\n    </a>\n  </div><div class=\"text-caption\">Nasławice Ghoul</div>\n</li>","postedSingleVideoPage":true},{"id":"monster-CwmpVuxp","date":"2018-07-04T00:52:03.416Z","caption":"Cordwood Bat","postedToGit":true,"htmlFragment":"<li class=\"pane\">\n  <div class=\"time-stamp entry-meta\">\n    <a href=\"monster-CwmpVuxp.html\">\n      <time datetime=\"2018-07-04T00:52:03.416Z\">2018-7-3 20:52:03</time>\n    </a>\n  </div><div class=\"text-caption\">Cordwood Bat</div>\n</li>","postedSingleVideoPage":true},{"id":"monster-JtEUtoqB","date":"2018-07-04T06:52:02.757Z","caption":"Sebum Wraith","postedToGit":true,"htmlFragment":"<li class=\"pane\">\n  <div class=\"time-stamp entry-meta\">\n    <a href=\"monster-JtEUtoqB.html\">\n      <time datetime=\"2018-07-04T06:52:02.757Z\">2018-7-4 02:52:02</time>\n    </a>\n  </div><div class=\"text-caption\">Sebum Wraith</div>\n</li>","postedSingleVideoPage":true},{"id":"monster-yjtopdFO","date":"2018-07-04T15:52:02.418Z","caption":"Graphite Fearow","postedToGit":true,"htmlFragment":"<li class=\"pane\">\n  <div class=\"time-stamp entry-meta\">\n    <a href=\"monster-yjtopdFO.html\">\n      <time datetime=\"2018-07-04T15:52:02.418Z\">2018-7-4 11:52:02</time>\n    </a>\n  </div><div class=\"text-caption\">Graphite Fearow</div>\n</li>","postedSingleVideoPage":true},{"id":"monster-TYNxXNni","date":"2018-07-05T00:52:03.343Z","caption":"Financial Manager Gastrodon","postedToGit":true,"htmlFragment":"<li class=\"pane\">\n  <div class=\"time-stamp entry-meta\">\n    <a href=\"monster-TYNxXNni.html\">\n      <time datetime=\"2018-07-05T00:52:03.343Z\">2018-7-4 20:52:03</time>\n    </a>\n  </div><div class=\"text-caption\">Financial Manager Gastrodon</div>\n</li>","postedSingleVideoPage":true},{"id":"monster-PLlbkSvu","date":"2018-07-05T06:52:02.785Z","caption":"Archipelago Sea Wallmaster","postedToGit":true,"htmlFragment":"<li class=\"pane\">\n  <div class=\"time-stamp entry-meta\">\n    <a href=\"monster-PLlbkSvu.html\">\n      <time datetime=\"2018-07-05T06:52:02.785Z\">2018-7-5 02:52:02</time>\n    </a>\n  </div><div class=\"text-caption\">Archipelago Sea Wallmaster</div>\n</li>","postedSingleVideoPage":true},{"id":"monster-QhNmoPLY","date":"2018-07-05T15:52:02.487Z","caption":"NewRelic Cthugha","postedToGit":true,"htmlFragment":"<li class=\"pane\">\n  <div class=\"time-stamp entry-meta\">\n    <a href=\"monster-QhNmoPLY.html\">\n      <time datetime=\"2018-07-05T15:52:02.487Z\">2018-7-5 11:52:02</time>\n    </a>\n  </div><div class=\"text-caption\">NewRelic Cthugha</div>\n</li>","postedSingleVideoPage":true},{"id":"monster-ISMLsKBc","date":"2018-07-06T00:52:03.348Z","caption":"Scala Stinkbug","postedToGit":true,"htmlFragment":"<li class=\"pane\">\n  <div class=\"time-stamp entry-meta\">\n    <a href=\"monster-ISMLsKBc.html\">\n      <time datetime=\"2018-07-06T00:52:03.348Z\">2018-7-5 20:52:03</time>\n    </a>\n  </div><div class=\"text-caption\">Scala Stinkbug</div>\n</li>","postedSingleVideoPage":true},{"id":"monster-bAmCTAKr","date":"2018-07-06T06:52:02.641Z","caption":"Cotton Digester","postedToGit":true,"htmlFragment":"<li class=\"pane\">\n  <div class=\"time-stamp entry-meta\">\n    <a href=\"monster-bAmCTAKr.html\">\n      <time datetime=\"2018-07-06T06:52:02.641Z\">2018-7-6 02:52:02</time>\n    </a>\n  </div><div class=\"text-caption\">Cotton Digester</div>\n</li>","postedSingleVideoPage":true},{"id":"monster-laSUVGen","date":"2018-07-06T15:52:02.753Z","caption":"Peony Avoral","postedToGit":true,"htmlFragment":"<li class=\"pane\">\n  <div class=\"time-stamp entry-meta\">\n    <a href=\"monster-laSUVGen.html\">\n      <time datetime=\"2018-07-06T15:52:02.753Z\">2018-7-6 11:52:02</time>\n    </a>\n  </div><div class=\"text-caption\">Peony Avoral</div>\n</li>","postedSingleVideoPage":true},{"id":"monster-oAshwzXw","date":"2018-07-07T00:52:03.134Z","caption":"Pink Sherbert Nightmare","postedToGit":true,"htmlFragment":"<li class=\"pane\">\n  <div class=\"time-stamp entry-meta\">\n    <a href=\"monster-oAshwzXw.html\">\n      <time datetime=\"2018-07-07T00:52:03.134Z\">2018-7-6 20:52:03</time>\n    </a>\n  </div><div class=\"text-caption\">Pink Sherbert Nightmare</div>\n</li>","postedSingleVideoPage":true},{"id":"monster-HQDccBOe","date":"2018-07-07T06:52:02.730Z","caption":"Cooper Dholes","postedToGit":true,"htmlFragment":"<li class=\"pane\">\n  <div class=\"time-stamp entry-meta\">\n    <a href=\"monster-HQDccBOe.html\">\n      <time datetime=\"2018-07-07T06:52:02.730Z\">2018-7-7 02:52:02</time>\n    </a>\n  </div><div class=\"text-caption\">Cooper Dholes</div>\n</li>","postedSingleVideoPage":true},{"id":"monster-pTYtJCqc","date":"2018-07-07T15:52:02.820Z","caption":"Roving Bot","postedToGit":true,"htmlFragment":"<li class=\"pane\">\n  <div class=\"time-stamp entry-meta\">\n    <a href=\"monster-pTYtJCqc.html\">\n      <time datetime=\"2018-07-07T15:52:02.820Z\">2018-7-7 11:52:02</time>\n    </a>\n  </div><div class=\"text-caption\">Roving Bot</div>\n</li>","postedSingleVideoPage":true},{"id":"monster-AFpMfOss","date":"2018-07-08T00:52:02.843Z","caption":"Jasmine Doomknocker","postedToGit":true,"htmlFragment":"<li class=\"pane\">\n  <div class=\"time-stamp entry-meta\">\n    <a href=\"monster-AFpMfOss.html\">\n      <time datetime=\"2018-07-08T00:52:02.843Z\">2018-7-7 20:52:02</time>\n    </a>\n  </div><div class=\"text-caption\">Jasmine Doomknocker</div>\n</li>","postedSingleVideoPage":true},{"id":"monster-tIbkdEbp","date":"2018-07-08T06:52:02.341Z","caption":"Kindergarten Teacher Archon","postedToGit":true,"htmlFragment":"<li class=\"pane\">\n  <div class=\"time-stamp entry-meta\">\n    <a href=\"monster-tIbkdEbp.html\">\n      <time datetime=\"2018-07-08T06:52:02.341Z\">2018-7-8 02:52:02</time>\n    </a>\n  </div><div class=\"text-caption\">Kindergarten Teacher Archon</div>\n</li>","postedSingleVideoPage":true},{"id":"monster-oHLhrgkB","date":"2018-07-08T15:52:02.206Z","caption":"Twilio Great Race of Yith","postedToGit":true,"htmlFragment":"<li class=\"pane\">\n  <div class=\"time-stamp entry-meta\">\n    <a href=\"monster-oHLhrgkB.html\">\n      <time datetime=\"2018-07-08T15:52:02.206Z\">2018-7-8 11:52:02</time>\n    </a>\n  </div><div class=\"text-caption\">Twilio Great Race of Yith</div>\n</li>","postedSingleVideoPage":true},{"id":"monster-LCbXmdxI","date":"2018-07-09T00:52:03.413Z","caption":"Nickel Rast","postedToGit":true,"htmlFragment":"<li class=\"pane\">\n  <div class=\"time-stamp entry-meta\">\n    <a href=\"monster-LCbXmdxI.html\">\n      <time datetime=\"2018-07-09T00:52:03.413Z\">2018-7-8 20:52:03</time>\n    </a>\n  </div><div class=\"text-caption\">Nickel Rast</div>\n</li>","postedSingleVideoPage":true},{"id":"monster-jYTBjYRV","date":"2018-07-09T06:52:02.174Z","caption":"Foundation Bronzor","postedToGit":true,"htmlFragment":"<li class=\"pane\">\n  <div class=\"time-stamp entry-meta\">\n    <a href=\"monster-jYTBjYRV.html\">\n      <time datetime=\"2018-07-09T06:52:02.174Z\">2018-7-9 02:52:02</time>\n    </a>\n  </div><div class=\"text-caption\">Foundation Bronzor</div>\n</li>","postedSingleVideoPage":true},{"id":"monster-NlMHWdTa","date":"2018-07-09T15:52:02.825Z","caption":"Ruthenium Espeon","postedToGit":true,"htmlFragment":"<li class=\"pane\">\n  <div class=\"time-stamp entry-meta\">\n    <a href=\"monster-NlMHWdTa.html\">\n      <time datetime=\"2018-07-09T15:52:02.825Z\">2018-7-9 11:52:02</time>\n    </a>\n  </div><div class=\"text-caption\">Ruthenium Espeon</div>\n</li>","postedSingleVideoPage":true},{"id":"monster-DYFdkNQG","date":"2018-07-10T00:52:03.276Z","caption":"Microcrystalline Wax Elder Thing","postedToGit":true,"htmlFragment":"<li class=\"pane\">\n  <div class=\"time-stamp entry-meta\">\n    <a href=\"monster-DYFdkNQG.html\">\n      <time datetime=\"2018-07-10T00:52:03.276Z\">2018-7-9 20:52:03</time>\n    </a>\n  </div><div class=\"text-caption\">Microcrystalline Wax Elder Thing</div>\n</li>","postedSingleVideoPage":true},{"id":"monster-RSZJwxlb","date":"2018-07-10T06:52:02.621Z","caption":"English Channel Behir","postedToGit":true,"htmlFragment":"<li class=\"pane\">\n  <div class=\"time-stamp entry-meta\">\n    <a href=\"monster-RSZJwxlb.html\">\n      <time datetime=\"2018-07-10T06:52:02.621Z\">2018-7-10 02:52:02</time>\n    </a>\n  </div><div class=\"text-caption\">English Channel Behir</div>\n</li>","postedSingleVideoPage":true},{"id":"monster-jjaKAPlz","date":"2018-07-10T15:52:02.538Z","caption":"Barber Shrew","postedToGit":true,"htmlFragment":"<li class=\"pane\">\n  <div class=\"time-stamp entry-meta\">\n    <a href=\"monster-jjaKAPlz.html\">\n      <time datetime=\"2018-07-10T15:52:02.538Z\">2018-7-10 11:52:02</time>\n    </a>\n  </div><div class=\"text-caption\">Barber Shrew</div>\n</li>","postedSingleVideoPage":true},{"id":"monster-OQkbxuJY","date":"2018-07-11T00:52:02.687Z","caption":"Tulip Pikachu","postedToGit":true,"htmlFragment":"<li class=\"pane\">\n  <div class=\"time-stamp entry-meta\">\n    <a href=\"monster-OQkbxuJY.html\">\n      <time datetime=\"2018-07-11T00:52:02.687Z\">2018-7-10 20:52:02</time>\n    </a>\n  </div><div class=\"text-caption\">Tulip Pikachu</div>\n</li>","postedSingleVideoPage":true},{"id":"monster-FEjdoBeo","date":"2018-07-11T06:52:02.786Z","caption":"Visayan Sea Dryad","postedToGit":true,"htmlFragment":"<li class=\"pane\">\n  <div class=\"time-stamp entry-meta\">\n    <a href=\"monster-FEjdoBeo.html\">\n      <time datetime=\"2018-07-11T06:52:02.786Z\">2018-7-11 02:52:02</time>\n    </a>\n  </div><div class=\"text-caption\">Visayan Sea Dryad</div>\n</li>","postedSingleVideoPage":true},{"id":"monster-cjmWaOuT","date":"2018-07-11T15:52:02.887Z","caption":"Minion Lemur","postedToGit":true,"htmlFragment":"<li class=\"pane\">\n  <div class=\"time-stamp entry-meta\">\n    <a href=\"monster-cjmWaOuT.html\">\n      <time datetime=\"2018-07-11T15:52:02.887Z\">2018-7-11 11:52:02</time>\n    </a>\n  </div><div class=\"text-caption\">Minion Lemur</div>\n</li>","postedSingleVideoPage":true},{"id":"monster-uXNtOrdk","date":"2018-07-12T00:52:03.185Z","caption":"CloudFront Bugbear","postedToGit":true,"htmlFragment":"<li class=\"pane\">\n  <div class=\"time-stamp entry-meta\">\n    <a href=\"monster-uXNtOrdk.html\">\n      <time datetime=\"2018-07-12T00:52:03.185Z\">2018-7-11 20:52:03</time>\n    </a>\n  </div><div class=\"text-caption\">CloudFront Bugbear</div>\n</li>","postedSingleVideoPage":true}]